[{"id":"377e7c1a.15ded4","type":"tab","label":"Transit Time","disabled":false,"info":""},{"id":"c0384c56.30e1","type":"inject","z":"377e7c1a.15ded4","name":"Inject","topic":"","payload":"{}","payloadType":"json","repeat":"","crontab":"","once":false,"onceDelay":0.1,"x":130,"y":360,"wires":[["e29e8986.cb6508"]]},{"id":"d0a6627b.18cc3","type":"http response","z":"377e7c1a.15ded4","name":"response","statusCode":"200","headers":{},"x":1040,"y":260,"wires":[]},{"id":"68fd0af1.5d5c34","type":"http in","z":"377e7c1a.15ded4","name":"[get] test","url":"/transittime","method":"get","upload":false,"swaggerDoc":"","x":140,"y":260,"wires":[["e29e8986.cb6508"]]},{"id":"c25af69.f111f08","type":"http in","z":"377e7c1a.15ded4","name":"[post] transittime","url":"/transittime","method":"post","upload":false,"swaggerDoc":"","x":340,"y":120,"wires":[["3e1da8b6.4c60d8"]]},{"id":"3e1da8b6.4c60d8","type":"change","z":"377e7c1a.15ded4","name":"","rules":[{"t":"set","p":"distance","pt":"msg","to":"payload.distance","tot":"msg"},{"t":"set","p":"config","pt":"msg","to":"payload.config","tot":"msg"}],"action":"","property":"","from":"","to":"","reg":false,"x":620,"y":120,"wires":[["fa3d437c.46c3c"]]},{"id":"4a35fcf0.d18e74","type":"comment","z":"377e7c1a.15ded4","name":"Curl Example","info":"curl -X POST http://localhost:1880/binpacking -H 'Content-type: application/json' -d '{ \"packages\": [ { \"name\": \"bh\", \"width\": 50, \"height\": 60, \"length\": 70, \"weight\": 28, \"quantity\": 3 } ], \"bins\": [ { \"name\": \"break\", \"width\": 100, \"height\": 100, \"length\": 120, \"weight\": 400 } ] }'","x":130,"y":220,"wires":[]},{"id":"41cb1c6c.851934","type":"json","z":"377e7c1a.15ded4","name":"","property":"payload","action":"str","pretty":true,"x":710,"y":380,"wires":[["e7834bd9.13da08"]]},{"id":"e7834bd9.13da08","type":"function","z":"377e7c1a.15ded4","name":"Convert HTML","func":"msg.payload = msg.payload.replace(/\\n/g, \"<br />\");\nreturn msg;","outputs":1,"noerr":0,"x":900,"y":380,"wires":[["3b0a6c14.0b3e24"]]},{"id":"d52a1ae6.ef1278","type":"change","z":"377e7c1a.15ded4","name":"","rules":[{"t":"set","p":"bins","pt":"msg","to":"payload.bins","tot":"msg"},{"t":"set","p":"packages","pt":"msg","to":"payload.packages","tot":"msg"},{"t":"set","p":"rotate","pt":"msg","to":"payload.rotate","tot":"msg"}],"action":"","property":"","from":"","to":"","reg":false,"x":460,"y":420,"wires":[["fa3d437c.46c3c"]]},{"id":"3b0a6c14.0b3e24","type":"ui_toast","z":"377e7c1a.15ded4","position":"dialog","displayTime":"3","highlight":"","sendall":false,"outputs":1,"ok":"OK","cancel":"","raw":true,"topic":"","name":"","x":1110,"y":380,"wires":[[]]},{"id":"b0f14cbd.f1a95","type":"ui_template","z":"377e7c1a.15ded4","group":"c72a542b.d89588","name":"HTML","order":0,"width":"12","height":"10","format":"<script src=\"https://ajax.googleapis.com/ajax/libs/jquery/3.3.1/jquery.min.js\">\n</script>\n<h1>Inputs</h1>\n<div class=\"container\" >\n <div class='element' id='div'>\n Distance : <input type='text' placeholder='distance' id='distance' size=5 value=500><br><br>\n Speed : <input type='text' placeholder='speed' id='speed' size=5 value=60><br><br>\n Driving Time : <input type='text' placeholder='drivingTime' id='drivingTime' size=5 value=4><br><br>\n Max Driving Time : <input type='text' placeholder='maxDrivingTime' id='maxDrivingTime' size=5 value=12><br><br>\n Break Time : <input type='text' placeholder='breakTime' id='breakTime' size=3 value=0.5><br><br>\n Rest Time : <input type='text' placeholder='restTime' id='restTime' size=5 value=8><br><br>\n </div>\n</div>\n<script>\n this.scope.action = function() {\n return { distance: $(\"#distance\").val(), config: { speed: $(\"#speed\").val(), drivingTime: $(\"#drivingTime\").val(), maxDrivingTime: $(\"#maxDrivingTime\").val(), breakTime: $(\"#breakTime\").val(), restTime: $(\"#restTime\").val() } }; \n }\n</script>\n<md-button ng-click=\"send({payload:action()})\">GO</md-button>","storeOutMessages":true,"fwdInMessages":true,"templateScope":"local","x":170,"y":560,"wires":[["d52a1ae6.ef1278"]]},{"id":"9fe93a28.84d568","type":"comment","z":"377e7c1a.15ded4","name":"UI TransitTime","info":"","x":140,"y":500,"wires":[]},{"id":"dbf4dbe9.fd80c8","type":"comment","z":"377e7c1a.15ded4","name":"Curl Transit Time","info":"curl -X POST http://localhost:1880/transittime -H 'Content-type: application/json' -d '{ \"distance\": 500, \"config\": {\"speed\":60,\"drivingTime\":4,\"maxDrivingTime\":12,\"breakTime\":0.5,\"restTime\":8}}'","x":340,"y":60,"wires":[]},{"id":"fa3d437c.46c3c","type":"transitTime","z":"377e7c1a.15ded4","name":"","x":610,"y":260,"wires":[["d0a6627b.18cc3","41cb1c6c.851934"]]},{"id":"e29e8986.cb6508","type":"change","z":"377e7c1a.15ded4","name":"","rules":[{"t":"set","p":"payload.distance","pt":"msg","to":"500","tot":"num"},{"t":"set","p":"payload.config","pt":"msg","to":"{\"speed\":60,\"drivingTime\":4,\"maxDrivingTime\":12,\"breakTime\":0.5,\"restTime\":8}","tot":"json"}],"action":"","property":"","from":"","to":"","reg":false,"x":320,"y":320,"wires":[["fa3d437c.46c3c"]]},{"id":"c72a542b.d89588","type":"ui_group","z":"","name":"Default","tab":"2deae1bc.4f783e","order":1,"disp":true,"width":"12","collapse":false},{"id":"2deae1bc.4f783e","type":"ui_tab","z":"","name":"Home","icon":"dashboard","disabled":false,"hidden":false}]
